autodla/__init__.py
autodla/connectors/fastapi.py
autodla/dbs/__init__.py
autodla/dbs/memorydb.py
autodla/dbs/postgresdb.py
autodla/engine/__init__.py
autodla/engine/data_conversion.py
autodla/engine/db.py
autodla/engine/interfaces.py
autodla/engine/lambda_conversion.py
autodla/engine/object.py
autodla/engine/web_connection.py
autodla/static/__init__.py
autodla/static/index.html
autodla/static/vite.svg
autodla/static/assets/__init__.py
autodla/static/assets/autodla-icon.png
autodla/static/assets/index-BNLJO5AD.css
autodla/static/assets/index-C7jLKPeh.js
autodla/utils/__init__.py
autodla/utils/data_generation.py
autodla/utils/df_tools.py
autodla/utils/logger.py
autodla/utils/watchdog.py
autodla-0.2.8.dist-info/licenses/LICENSE
autodla-0.2.8.dist-info/METADATA
autodla-0.2.8.dist-info/WHEEL
autodla-0.2.8.dist-info/top_level.txt
autodla-0.2.8.dist-info/RECORD
